oraclebmc/__init__.py
oraclebmc/base_client.py
oraclebmc/config.py
oraclebmc/constants.py
oraclebmc/decorators.py
oraclebmc/exceptions.py
oraclebmc/regions.py
oraclebmc/request.py
oraclebmc/response.py
oraclebmc/service_endpoints.py
oraclebmc/signer.py
oraclebmc/util.py
oraclebmc/version.py
oraclebmc/waiter.py
oraclebmc/audit/__init__.py
oraclebmc/audit/audit_client.py
oraclebmc/audit/models/__init__.py
oraclebmc/audit/models/audit_event.py
oraclebmc/audit/models/configuration.py
oraclebmc/audit/models/update_configuration_details.py
oraclebmc/auth/__init__.py
oraclebmc/auth/auth_utils.py
oraclebmc/auth/certificate_retriever.py
oraclebmc/auth/federation_client.py
oraclebmc/auth/security_token_container.py
oraclebmc/auth/session_key_supplier.py
oraclebmc/auth/signers/__init__.py
oraclebmc/auth/signers/instance_principals_security_token_signer.py
oraclebmc/auth/signers/security_token_signer.py
oraclebmc/core/__init__.py
oraclebmc/core/blockstorage_client.py
oraclebmc/core/compute_client.py
oraclebmc/core/virtual_network_client.py
oraclebmc/core/models/__init__.py
oraclebmc/core/models/attach_boot_volume_details.py
oraclebmc/core/models/attach_i_scsi_volume_details.py
oraclebmc/core/models/attach_paravirtualized_volume_details.py
oraclebmc/core/models/attach_vnic_details.py
oraclebmc/core/models/attach_volume_details.py
oraclebmc/core/models/boot_volume.py
oraclebmc/core/models/boot_volume_attachment.py
oraclebmc/core/models/bulk_add_virtual_circuit_public_prefixes_details.py
oraclebmc/core/models/bulk_delete_virtual_circuit_public_prefixes_details.py
oraclebmc/core/models/capture_console_history_details.py
oraclebmc/core/models/connect_local_peering_gateways_details.py
oraclebmc/core/models/connect_remote_peering_connections_details.py
oraclebmc/core/models/console_history.py
oraclebmc/core/models/cpe.py
oraclebmc/core/models/create_cpe_details.py
oraclebmc/core/models/create_cross_connect_details.py
oraclebmc-1.3.17.dist-info/DESCRIPTION.rst
oraclebmc-1.3.17.dist-info/LICENSE.txt
oraclebmc-1.3.17.dist-info/METADATA
oraclebmc-1.3.17.dist-info/RECORD
oraclebmc-1.3.17.dist-info/WHEEL
oraclebmc-1.3.17.dist-info/metadata.json
oraclebmc-1.3.17.dist-info/top_level.txt
