Metadata-Version: 2.0
Name: oraclebmc
Version: 1.3.17
Summary: Oracle Cloud Infrastructure Python SDK
Home-page: https://oracle-cloud-infrastructure-python-sdk.readthedocs.io/en/latest/index.html
Author: Oracle
Author-email: joe.levy@oracle.com
License: Universal Permissive License 1.0 or Apache License 2.0
Platform: UNKNOWN
Classifier: Development Status :: 5 - Production/Stable
Classifier: Intended Audience :: Developers
Classifier: License :: OSI Approved :: Apache Software License
Classifier: License :: OSI Approved :: Universal Permissive License (UPL)
Classifier: Programming Language :: Python :: 2.7
Classifier: Programming Language :: Python :: 3.5
Requires-Dist: PyJWT (==1.5.3)
Requires-Dist: certifi
Requires-Dist: configparser (==3.5.0)
Requires-Dist: cryptography (==2.1.3)
Requires-Dist: httpsig-cffi (==15.0.0)
Requires-Dist: pyOpenSSL (<=17.4.0)
Requires-Dist: python-dateutil (==2.5.3)
Requires-Dist: pytz (==2016.10)
Requires-Dist: requests (==2.18.4)
Requires-Dist: six (==1.11.0)
